mlog/__init__.py
mlog/cli.py
mlog/mlog.py
pymlog-0.0.26.dist-info/LICENSE.md
pymlog-0.0.26.dist-info/METADATA
pymlog-0.0.26.dist-info/WHEEL
pymlog-0.0.26.dist-info/entry_points.txt
pymlog-0.0.26.dist-info/top_level.txt
pymlog-0.0.26.dist-info/RECORD
