Metadata-Version: 2.1
Name: pymlog
Version: 0.0.26
Summary: A minimal logging utility for machine learning experiments
Author: gsprd
License: MIT License        
Project-URL: Homepage, https://github.com/g-s-p-r-d/mlog
Classifier: Programming Language :: Python :: 3
Classifier: License :: OSI Approved :: MIT License
Classifier: Operating System :: OS Independent
Requires-Python: >=3.7
License-File: LICENSE.md
Requires-Dist: pandas (>=1.4)
Requires-Dist: matplotlib (>=3.5)
